shove_lmdb/__init__.py
shove_lmdb/store.py
shove_lmdb/test/__init__.py
shove_lmdb/test/test_ldbstore.py
shove_lmdb-0.1.0.dist-info/DESCRIPTION.rst
shove_lmdb-0.1.0.dist-info/METADATA
shove_lmdb-0.1.0.dist-info/RECORD
shove_lmdb-0.1.0.dist-info/WHEEL
shove_lmdb-0.1.0.dist-info/entry_points.txt
shove_lmdb-0.1.0.dist-info/metadata.json
shove_lmdb-0.1.0.dist-info/pbr.json
shove_lmdb-0.1.0.dist-info/top_level.txt
